{
  "dependencies": [
    {
      "name": "black",
      "version": "^21.6b0",
      "type": "devenv"
    },
    {
      "name": "flake8",
      "version": "^3.9.2",
      "type": "devenv"
    },
    {
      "name": "hypothesis",
      "version": "^4.36",
      "type": "devenv"
    },
    {
      "name": "isort",
      "version": "^5.8.0",
      "type": "devenv"
    },
    {
      "name": "mypy",
      "version": "^0.901",
      "type": "devenv"
    },
    {
      "name": "pytest",
      "version": "^6.2.4",
      "type": "devenv"
    },
    {
      "name": "types-pkg_resources",
      "version": "^0.1.2",
      "type": "devenv"
    },
    {
      "name": "types-pytz",
      "version": "^0.1.0",
      "type": "devenv"
    },
    {
      "name": "types-toml",
      "version": "^0.1.1",
      "type": "devenv"
    },
    {
      "name": "docopt",
      "version": "^0.6.2",
      "type": "runtime"
    },
    {
      "name": "jsonpath-rw",
      "version": "^1.4",
      "type": "runtime"
    },
    {
      "name": "jsonschema",
      "version": "^3.0",
      "type": "runtime"
    },
    {
      "name": "python",
      "version": "^3.7",
      "type": "runtime"
    },
    {
      "name": "toml",
      "version": "^0.10.0",
      "type": "runtime"
    }
  ],
  "//": "~~ Generated by projen. To modify, edit .projenrc.js and run \"npx projen\"."
}
